performance_hints/__init__.py
performance_hints/decorators.py
performance_hints/analyzers/__init__.py
performance_hints/analyzers/ast_analyzer.py
performance_hints/config/__init__.py
performance_hints/config/settings.py
performance_hints/detectors/__init__.py
performance_hints/detectors/base.py
performance_hints/detectors/loops.py
performance_hints/detectors/timing.py
performance_hints/reporters/__init__.py
performance_hints/reporters/base.py
performance_hints/reporters/console.py
py_performance_hints-0.1.0.dist-info/licenses/LICENSE
py_performance_hints-0.1.0.dist-info/METADATA
py_performance_hints-0.1.0.dist-info/WHEEL
py_performance_hints-0.1.0.dist-info/top_level.txt
py_performance_hints-0.1.0.dist-info/RECORD
