Metadata-Version: 2.4
Name: py-performance-hints
Version: 0.1.0
Summary: Intelligent performance bottleneck detection for Python developers
Author-email: Rajaul Uddin <uddin.rajaul@gmail.com>
License: MIT License
Project-URL: Homepage, https://github.com/yourusername/py-performance-hints
Project-URL: Repository, https://github.com/yourusername/py-performance-hints
Keywords: performance,profiling,optimization,development,debugging
Classifier: Development Status :: 3 - Alpha
Classifier: Intended Audience :: Developers
Classifier: License :: OSI Approved :: MIT License
Classifier: Programming Language :: Python :: 3
Classifier: Programming Language :: Python :: 3.8
Classifier: Programming Language :: Python :: 3.9
Classifier: Programming Language :: Python :: 3.10
Classifier: Programming Language :: Python :: 3.11
Classifier: Programming Language :: Python :: 3.12
Classifier: Programming Language :: Python :: 3.13
Classifier: Topic :: Software Development :: Debuggers
Classifier: Topic :: Software Development :: Quality Assurance
Requires-Python: >=3.8
License-File: LICENSE
Provides-Extra: dev
Requires-Dist: pytest>=7.0.0; extra == "dev"
Requires-Dist: black>=22.0.0; extra == "dev"
Requires-Dist: flake8>=5.0.0; extra == "dev"
Dynamic: license-file
Dynamic: requires-python
